Workbook

Sheet Comps
A1: HDFC Bank — Trading Comparables
A2: All figures as reported on Screener.in / company filings, accessed 15-Jul-2026. Consolidated financials. Currency: INR.
A4: Company | B4: Price (₹) | C4: Mkt Cap (₹ Cr) | D4: EPS (₹) | E4: P/E (x) | F4: Book Value /Share (₹) | G4: P/B (x) | H4: ROE (%)
A5: HDFC Bank (Target) | B5: 799 | C5: 1230412 | D5: 49.39 | E5: =B5/D5 -> 16.177364 | F5: 378 | G5: =B5/F5 -> 2.1137566 | H5: 0.138
A6: ICICI Bank | B6: 1417 | C6: 1016736 | D6: 75.78 | E6: =B6/D6 -> 18.698865 | F6: 503 | G6: =B6/F6 -> 2.8170974 | H6: 0.161
A7: Axis Bank | B7: 1262 | C7: 392307 | D7: 84.89 | E7: =B7/D7 -> 14.866298 | F7: 687 | G7: =B7/F7 -> 1.8369723 | H7: 0.132
A8: Kotak Mahindra Bank | B8: 377 | C8: 375431 | D8: 19.39 | E8: =B8/D8 -> 19.443012 | F8: 182 | G8: =B8/F8 -> 2.0714286 | H8: 0.112
A9: State Bank of India | B9: 1074 | C9: 1007153 | D9: 86.4 | E9: =B9/D9 -> 12.430556 | F9: 611.73 | G9: =B9/F9 -> 1.7556765 | H9: 0.1435
A10: Source: Screener.in company pages (HDFCBANK, ICICIBANK, AXISBANK, KOTAKBANK, SBIN — consolidated), accessed 15-Jul-2026.
A12: Peer Set Statistics (excl. HDFC Bank)
A13: Metric | E13: P/E (x) | G13: P/B (x) | H13: ROE (%)
A14: Peer Average | E14: =AVERAGE(E6:E9) -> 16.359683 | G14: =AVERAGE(G6:G9) -> 2.1202937 | H14: =AVERAGE(H6:H9) -> 0.137125
A15: Peer Median | E15: =MEDIAN(E6:E9) -> 16.782581 | G15: =MEDIAN(G6:G9) -> 1.9542005 | H15: =MEDIAN(H6:H9) -> 0.13775
A17: Implied Valuation — HDFC Bank
A18: Method | B18: Multiple Applied | C18: HDFC Metric | D18: Implied Price (₹) | E18: vs Current Price
A19: P/E — Peer Average | B19: =E14 -> 16.359683 | C19: =D5 -> 49.39 | D19: =B19*C19 -> 808.00472 | E19: =D19/$B$5-1 -> 0.011269988
A20: P/E — Peer Median | B20: =E15 -> 16.782581 | C20: =D5 -> 49.39 | D20: =B20*C20 -> 828.89169 | E20: =D20/$B$5-1 -> 0.03741138
A21: P/B — Peer Average | B21: =G14 -> 2.1202937 | C21: =F5 -> 378 | D21: =B21*C21 -> 801.47102 | E21: =D21/$B$5-1 -> 0.0030926455
A22: P/B — Peer Median | B22: =G15 -> 1.9542005 | C22: =F5 -> 378 | D22: =B22*C22 -> 738.68777 | E22: =D22/$B$5-1 -> -0.07548464

Sheet DDM
A1: HDFC Bank — Dividend Discount Model
A2: Two-stage DDM. Banks are valued on DDM/comps rather than a standard FCF DCF, since leverage is core to the business, not a financing choice.
A4: Assumptions
A5: Current EPS, FY26 (₹) | B5: 49.39 | C5: Source: Screener.in, HDFC Bank consolidated P&L, FY ending Mar-2026.
A6: Dividend Payout Ratio, FY26 | B6: 0.31 | C6: Source: Screener.in — reported dividend payout %, FY26.
A7: Current ROE (₹) | B7: 0.138 | C7: Source: Screener.in — trailing ROE.
A8: Risk-free rate (10Y India G-Sec) | B8: 0.069 | C8: Approximate — verify against current 10-year G-Sec yield before use.
A9: Equity Risk Premium — India | B9: 0.065 | C9: Commonly used long-run India equity risk premium estimate — adjust per house view.
A10: Beta (HDFC Bank, vs Nifty) | B10: 1.05 | C10: Typical large private-bank beta; adjust to your source (Bloomberg/NSE).
A11: High-growth phase length (years) | B11: 5 | C11: Assumption — user-adjustable.
A12: Terminal growth rate (g) | B12: 0.06 | C12: Long-run nominal GDP growth proxy — must stay below cost of equity.
A14: Cost of Equity (CAPM)
A15: Cost of Equity, Ke = Rf + Beta × ERP | B15: =B8+B10*B9 -> 0.13725
A17: High-Growth Phase Dividend Rate, g1 = ROE × (1 - Payout) | B17: =B7*(1-B6) -> 0.09522
A18: Current DPS, FY26 (₹) = EPS × Payout | B18: =B5*B6 -> 15.3109
A21: Dividend Projection & Present Value
B22: Year 1 | C22: Year 2 | D22: Year 3 | E22: Year 4 | F22: Year 5 | G22: Terminal
A23: Growth rate applied | B23: =B17 -> 0.09522 | C23: =B17 -> 0.09522 | D23: =B17 -> 0.09522 | E23: =B17 -> 0.09522 | F23: =B17 -> 0.09522 | G23: =B12 -> 0.06
A24: Projected DPS (₹) | B24: =B18*(1+B23) -> 16.768804 | C24: =B24*(1+C23) -> 18.365529 | D24: =C24*(1+D23) -> 20.114295 | E24: =D24*(1+E23) -> 22.029578 | F24: =E24*(1+F23) -> 24.127235 | G24: =F24*(1+B12)/(B15-B12) -> 331.06626
A25: Discount factor @ Ke | B25: =1/(1+B15)^1 -> 0.87931413 | C25: =1/(1+B15)^2 -> 0.77319335 | D25: =1/(1+B15)^3 -> 0.67987984 | E25: =1/(1+B15)^4 -> 0.59782795 | F25: =1/(1+B15)^5 -> 0.52567857 | G25: =F25 -> 0.52567857
A26: PV of Dividend (₹) | B26: =B24*B25 -> 14.745046 | C26: =C24*C25 -> 14.200105 | D26: =D24*D25 -> 13.675304 | E26: =E24*E25 -> 13.169898 | F26: =F24*F25 -> 12.68317 | G26: =G24*G25 -> 174.03444
A28: Sum of PV of Dividends, Yr 1-5 (₹) | B28: =SUM(B26:F26) -> 68.473523
A29: PV of Terminal Value (₹) | B29: =G26 -> 174.03444
A30: Intrinsic Value per Share (₹) | B30: =B28+B29 -> 242.50796
A31: Current Market Price (₹) | B31: =Comps!B5 -> 799
A32: Implied Upside / (Downside) | B32: =B30/B31-1 -> -0.69648565
A34: Sensitivity — Intrinsic Value (₹) by Cost of Equity vs. Terminal Growth
A35: Base case (Ke=13.7%, g=6.0%) implies HDFC trades well above intrinsic value — a common result for low dividend-payout banks under a plain DDM, since most value creation is retained rather than paid out. Use this grid to see how sensitive the answer is to the Ke/g spread, and pair with the Comps tab rather than relying on DDM alone.
A37: Ke \ g | B37: =B12+(-0.01) -> 0.05 | C37: =B12+(-0.005) -> 0.055 | D37: =B12+(0) -> 0.06 | E37: =B12+(0.005) -> 0.065 | F37: =B12+(0.01) -> 0.07
A38: =B15+(-0.01) -> 0.12725 | B38: =SUMPRODUCT(B18*(1+B17)^ROW(INDIRECT("1:5"))/(1+$A38)^ROW(INDIRECT("1:5")))+(B18*(1+B17)^5*(1+B$37)/($A38-B$37))/(1+$A38)^5 -> 250.44688 | C38: =SUMPRODUCT(B18*(1+B17)^ROW(INDIRECT("1:5"))/(1+$A38)^ROW(INDIRECT("1:5")))+(B18*(1+B17)^5*(1+C$37)/($A38-C$37))/(1+$A38)^5 -> 263.83317 | D38: =SUMPRODUCT(B18*(1+B17)^ROW(INDIRECT("1:5"))/(1+$A38)^ROW(INDIRECT("1:5")))+(B18*(1+B17)^5*(1+D$37)/($A38-D$37))/(1+$A38)^5 -> 279.20999 | E38: =SUMPRODUCT(B18*(1+B17)^ROW(INDIRECT("1:5"))/(1+$A38)^ROW(INDIRECT("1:5")))+(B18*(1+B17)^5*(1+E$37)/($A38-E$37))/(1+$A38)^5 -> 297.05698 | F38: =SUMPRODUCT(B18*(1+B17)^ROW(INDIRECT("1:5"))/(1+$A38)^ROW(INDIRECT("1:5")))+(B18*(1+B17)^5*(1+F$37)/($A38-F$37))/(1+$A38)^5 -> 318.02134
A39: =B15+(-0.005) -> 0.13225 | B39: =SUMPRODUCT(B18*(1+B17)^ROW(INDIRECT("1:5"))/(1+$A39)^ROW(INDIRECT("1:5")))+(B18*(1+B17)^5*(1+B$37)/($A39-B$37))/(1+$A39)^5 -> 234.88255 | C39: =SUMPRODUCT(B18*(1+B17)^ROW(INDIRECT("1:5"))/(1+$A39)^ROW(INDIRECT("1:5")))+(B18*(1+B17)^5*(1+C$37)/($A39-C$37))/(1+$A39)^5 -> 246.435 | D39: =SUMPRODUCT(B18*(1+B17)^ROW(INDIRECT("1:5"))/(1+$A39)^ROW(INDIRECT("1:5")))+(B18*(1+B17)^5*(1+D$37)/($A39-D$37))/(1+$A39)^5 -> 259.5864 | E39: =SUMPRODUCT(B18*(1+B17)^ROW(INDIRECT("1:5"))/(1+$A39)^ROW(INDIRECT("1:5")))+(B18*(1+B17)^5*(1+E$37)/($A39-E$37))/(1+$A39)^5 -> 274.69339 | F39: =SUMPRODUCT(B18*(1+B17)^ROW(INDIRECT("1:5"))/(1+$A39)^ROW(INDIRECT("1:5")))+(B18*(1+B17)^5*(1+F$37)/($A39-F$37))/(1+$A39)^5 -> 292.22721
A40: =B15+(0) -> 0.13725 | B40: =SUMPRODUCT(B18*(1+B17)^ROW(INDIRECT("1:5"))/(1+$A40)^ROW(INDIRECT("1:5")))+(B18*(1+B17)^5*(1+B$37)/($A40-B$37))/(1+$A40)^5 -> 221.10766 | C40: =SUMPRODUCT(B18*(1+B17)^ROW(INDIRECT("1:5"))/(1+$A40)^ROW(INDIRECT("1:5")))+(B18*(1+B17)^5*(1+C$37)/($A40-C$37))/(1+$A40)^5 -> 231.15735 | D40: =SUMPRODUCT(B18*(1+B17)^ROW(INDIRECT("1:5"))/(1+$A40)^ROW(INDIRECT("1:5")))+(B18*(1+B17)^5*(1+D$37)/($A40-D$37))/(1+$A40)^5 -> 242.50796 | E40: =SUMPRODUCT(B18*(1+B17)^ROW(INDIRECT("1:5"))/(1+$A40)^ROW(INDIRECT("1:5")))+(B18*(1+B17)^5*(1+E$37)/($A40-E$37))/(1+$A40)^5 -> 255.4296 | F40: =SUMPRODUCT(B18*(1+B17)^ROW(INDIRECT("1:5"))/(1+$A40)^ROW(INDIRECT("1:5")))+(B18*(1+B17)^5*(1+F$37)/($A40-F$37))/(1+$A40)^5 -> 270.27266
A41: =B15+(0.005) -> 0.14225 | B41: =SUMPRODUCT(B18*(1+B17)^ROW(INDIRECT("1:5"))/(1+$A41)^ROW(INDIRECT("1:5")))+(B18*(1+B17)^5*(1+B$37)/($A41-B$37))/(1+$A41)^5 -> 208.83112 | C41: =SUMPRODUCT(B18*(1+B17)^ROW(INDIRECT("1:5"))/(1+$A41)^ROW(INDIRECT("1:5")))+(B18*(1+B17)^5*(1+C$37)/($A41-C$37))/(1+$A41)^5 -> 217.63555 | D41: =SUMPRODUCT(B18*(1+B17)^ROW(INDIRECT("1:5"))/(1+$A41)^ROW(INDIRECT("1:5")))+(B18*(1+B17)^5*(1+D$37)/($A41-D$37))/(1+$A41)^5 -> 227.51042 | E41: =SUMPRODUCT(B18*(1+B17)^ROW(INDIRECT("1:5"))/(1+$A41)^ROW(INDIRECT("1:5")))+(B18*(1+B17)^5*(1+E$37)/($A41-E$37))/(1+$A41)^5 -> 238.6636 | F41: =SUMPRODUCT(B18*(1+B17)^ROW(INDIRECT("1:5"))/(1+$A41)^ROW(INDIRECT("1:5")))+(B18*(1+B17)^5*(1+F$37)/($A41-F$37))/(1+$A41)^5 -> 251.36046
A42: =B15+(0.01) -> 0.14725 | B42: =SUMPRODUCT(B18*(1+B17)^ROW(INDIRECT("1:5"))/(1+$A42)^ROW(INDIRECT("1:5")))+(B18*(1+B17)^5*(1+B$37)/($A42-B$37))/(1+$A42)^5 -> 197.82172 | C42: =SUMPRODUCT(B18*(1+B17)^ROW(INDIRECT("1:5"))/(1+$A42)^ROW(INDIRECT("1:5")))+(B18*(1+B17)^5*(1+C$37)/($A42-C$37))/(1+$A42)^5 -> 205.584 | D42: =SUMPRODUCT(B18*(1+B17)^ROW(INDIRECT("1:5"))/(1+$A42)^ROW(INDIRECT("1:5")))+(B18*(1+B17)^5*(1+D$37)/($A42-D$37))/(1+$A42)^5 -> 214.23593 | E42: =SUMPRODUCT(B18*(1+B17)^ROW(INDIRECT("1:5"))/(1+$A42)^ROW(INDIRECT("1:5")))+(B18*(1+B17)^5*(1+E$37)/($A42-E$37))/(1+$A42)^5 -> 223.93978 | F42: =SUMPRODUCT(B18*(1+B17)^ROW(INDIRECT("1:5"))/(1+$A42)^ROW(INDIRECT("1:5")))+(B18*(1+B17)^5*(1+F$37)/($A42-F$37))/(1+$A42)^5 -> 234.89979

Sheet Summary
A1: HDFC Bank — Valuation Summary
A2: Implied value per share (₹) across methodologies vs. current market price.
A4: Methodology | B4: Implied Value (₹)
A5: Comps — P/E (Peer Avg) | B5: =Comps!D19 -> 808.00472
A6: Comps — P/E (Peer Median) | B6: =Comps!D20 -> 828.89169
A7: Comps — P/B (Peer Avg) | B7: =Comps!D21 -> 801.47102
A8: Comps — P/B (Peer Median) | B8: =Comps!D22 -> 738.68777
A9: DDM — Intrinsic Value | B9: =DDM!B30 -> 242.50796
A10: Current Market Price | B10: =Comps!B5 -> 799
